{"objectID":"0.8_collectionsinterop.html#interop-with-data-classes","parent":"0.8_collectionsinterop.html","pageViews":0,"url":"https://kotlin.github.io/dataframe///collectionsinterop.html#interop-with-data-classes","version":"0.8","product":"","headings":"Interop with data classes","content":"data class Output(val a: Int, val b: Int, val c: Int) val result \u003d df2.toListOf\u003cOutput\u003e()","pageTitle":"Interop with Collections","metaDescription":"","type":"Documentation","breadcrumbs":"operations.md|Operations"}