{"objectID":"0.8_schemas.html","parent":"0.8_schemas.html","pageViews":0,"url":"https://kotlin.github.io/dataframe///schemas.html","version":"0.8","product":"","headings":"Working with Data Schemas","content":"In Jupyter environment DataFrame provides typed data access by automatic inference of DataSchema of new DataFrame instances and generation of schema-specific extension properties","pageTitle":"Working with Data Schemas","metaDescription":"","type":"Documentation","breadcrumbs":"overview.md|Overview"}