{"objectID":"0.9_createaccessor.html#computed-column-accessors","parent":"0.9_createaccessor.html","pageViews":0,"url":"https://kotlin.github.io/dataframe///createaccessor.html#computed-column-accessors","version":"0.9","product":"","headings":"Computed column accessors","content":"val age by column\u003cInt\u003e() val year by age.map { 2021 - it } df.filter { year \u003e 2000 }","pageTitle":"Create ColumnAccessor","metaDescription":"","type":"Documentation","breadcrumbs":"operations.md|Operations///create.md|Create"}